[{"fields": {"country": 6, "is_deleted": false}, "model": "party.party", "pk": 1}, {"fields": {"country": 3, "is_deleted": false}, "model": "party.party", "pk": 2}, {"fields": {"country": 4, "is_deleted": false}, "model": "party.party", "pk": 3}, {"fields": {"country": null, "is_deleted": false}, "model": "party.party", "pk": 4}, {"fields": {"country": 7, "is_deleted": false}, "model": "party.party", "pk": 5}, {"fields": {"country": 4, "is_deleted": false}, "model": "party.party", "pk": 6}, {"fields": {"country": 2, "is_deleted": false}, "model": "party.party", "pk": 7}, {"fields": {"country": 6, "is_deleted": false}, "model": "party.party", "pk": 8}, {"fields": {"country": null, "is_deleted": false}, "model": "party.party", "pk": 9}, {"fields": {"country": null, "is_deleted": false}, "model": "party.party", "pk": 10}, {"fields": {"country": null, "is_deleted": false}, "model": "party.party", "pk": 11}, {"fields": {"country": null, "is_deleted": false}, "model": "party.party", "pk": 12}, {"fields": {"country": null, "is_deleted": false}, "model": "party.party", "pk": 13}, {"fields": {"country": null, "is_deleted": false}, "model": "party.party", "pk": 14}, {"fields": {"country": null, "is_deleted": false}, "model": "party.party", "pk": 15}, {"fields": {"country": null, "is_deleted": false}, "model": "party.party", "pk": 16}, {"fields": {"country": null, "is_deleted": false}, "model": "party.party", "pk": 17}, {"fields": {"country": null, "is_deleted": false}, "model": "party.party", "pk": 18}, {"fields": {"country": null, "is_deleted": false}, "model": "party.party", "pk": 19}, {"fields": {"country": null, "is_deleted": false}, "model": "party.party", "pk": 20}, {"fields": {"country": null, "is_deleted": false}, "model": "party.party", "pk": 21}, {"fields": {"country": null, "is_deleted": false}, "model": "party.party", "pk": 22}, {"fields": {"country": null, "is_deleted": false}, "model": "party.party", "pk": 23}, {"fields": {"country": null, "is_deleted": false}, "model": "party.party", "pk": 24}, {"fields": {"country": null, "is_deleted": false}, "model": "party.party", "pk": 25}, {"fields": {"country": null, "is_deleted": false}, "model": "party.party", "pk": 26}, {"fields": {"country": null, "is_deleted": false}, "model": "party.party", "pk": 27}, {"fields": {"country": null, "is_deleted": false}, "model": "party.party", "pk": 28}, {"fields": {"country": null, "is_deleted": false}, "model": "party.party", "pk": 29}, {"fields": {"country": null, "is_deleted": false}, "model": "party.party", "pk": 30}, {"fields": {"country": null, "is_deleted": false}, "model": "party.party", "pk": 31}, {"fields": {"country": null, "is_deleted": false}, "model": "party.party", "pk": 32}, {"fields": {"country": null, "is_deleted": false}, "model": "party.party", "pk": 33}, {"fields": {"country": null, "is_deleted": false}, "model": "party.party", "pk": 34}, {"fields": {"country": null, "is_deleted": false}, "model": "party.party", "pk": 35}, {"fields": {"country": null, "is_deleted": false}, "model": "party.party", "pk": 36}, {"fields": {"country": null, "is_deleted": false}, "model": "party.party", "pk": 37}, {"fields": {"country": null, "is_deleted": false}, "model": "party.party", "pk": 38}, {"fields": {"country": null, "is_deleted": false}, "model": "party.party", "pk": 39}, {"fields": {"country": null, "is_deleted": false}, "model": "party.party", "pk": 40}, {"fields": {"country": null, "is_deleted": false}, "model": "party.party", "pk": 41}, {"fields": {"country": null, "is_deleted": false}, "model": "party.party", "pk": 42}, {"fields": {"country": null, "is_deleted": false}, "model": "party.party", "pk": 43}, {"fields": {"country": null, "is_deleted": false}, "model": "party.party", "pk": 44}, {"fields": {"country": null, "is_deleted": false}, "model": "party.party", "pk": 45}, {"fields": {"country": null, "is_deleted": false}, "model": "party.party", "pk": 46}, {"fields": {"country": null, "is_deleted": false}, "model": "party.party", "pk": 47}, {"fields": {"country": null, "is_deleted": false}, "model": "party.party", "pk": 48}, {"fields": {"country": null, "is_deleted": false}, "model": "party.party", "pk": 49}, {"fields": {"country": null, "is_deleted": false}, "model": "party.party", "pk": 50}, {"fields": {"country": null, "is_deleted": false}, "model": "party.party", "pk": 51}, {"fields": {"country": null, "is_deleted": false}, "model": "party.party", "pk": 52}, {"fields": {"country": null, "is_deleted": false}, "model": "party.party", "pk": 53}, {"fields": {"country": null, "is_deleted": false}, "model": "party.party", "pk": 54}, {"fields": {"country": null, "is_deleted": false}, "model": "party.party", "pk": 55}, {"fields": {"country": null, "is_deleted": false}, "model": "party.party", "pk": 56}, {"fields": {"country": null, "is_deleted": false}, "model": "party.party", "pk": 57}, {"fields": {"country": null, "is_deleted": false}, "model": "party.party", "pk": 58}, {"fields": {"country": null, "is_deleted": false}, "model": "party.party", "pk": 59}, {"fields": {"country": null, "is_deleted": false}, "model": "party.party", "pk": 60}, {"fields": {"country": null, "is_deleted": false}, "model": "party.party", "pk": 61}, {"fields": {"country": 3, "is_deleted": false}, "model": "party.party", "pk": 62}, {"fields": {"country": 6, "is_deleted": false}, "model": "party.party", "pk": 63}, {"fields": {"country": 4, "is_deleted": false}, "model": "party.party", "pk": 64}, {"fields": {"country": 2, "is_deleted": false}, "model": "party.party", "pk": 65}, {"fields": {"country": 4, "is_deleted": false}, "model": "party.party", "pk": 66}, {"fields": {"country": 6, "is_deleted": false}, "model": "party.party", "pk": 67}, {"fields": {"country": 1, "is_deleted": false}, "model": "party.party", "pk": 68}, {"fields": {"country": 2, "is_deleted": false}, "model": "party.party", "pk": 69}, {"fields": {"country": 4, "is_deleted": false}, "model": "party.party", "pk": 70}, {"fields": {"country": 5, "is_deleted": false}, "model": "party.party", "pk": 71}, {"fields": {"country": 2, "is_deleted": false}, "model": "party.party", "pk": 72}, {"fields": {"country": 4, "is_deleted": false}, "model": "party.party", "pk": 73}, {"fields": {"country": 6, "is_deleted": false}, "model": "party.party", "pk": 74}, {"fields": {"country": 5, "is_deleted": false}, "model": "party.party", "pk": 75}, {"fields": {"country": 7, "is_deleted": false}, "model": "party.party", "pk": 76}, {"fields": {"country": 5, "is_deleted": false}, "model": "party.party", "pk": 77}, {"fields": {"country": 7, "is_deleted": false}, "model": "party.party", "pk": 78}, {"fields": {"country": 7, "is_deleted": false}, "model": "party.party", "pk": 79}, {"fields": {"country": 1, "is_deleted": false}, "model": "party.party", "pk": 80}, {"fields": {"country": 4, "is_deleted": false}, "model": "party.party", "pk": 81}, {"fields": {"country": 4, "is_deleted": false}, "model": "party.party", "pk": 82}, {"fields": {"country": 2, "is_deleted": false}, "model": "party.party", "pk": 83}, {"fields": {"country": 3, "is_deleted": false}, "model": "party.party", "pk": 84}, {"fields": {"country": 4, "is_deleted": false}, "model": "party.party", "pk": 85}, {"fields": {"country": 3, "is_deleted": false}, "model": "party.party", "pk": 86}, {"fields": {"country": 5, "is_deleted": false}, "model": "party.party", "pk": 87}, {"fields": {"country": 2, "is_deleted": false}, "model": "party.party", "pk": 88}, {"fields": {"country": 5, "is_deleted": false}, "model": "party.party", "pk": 89}, {"fields": {"country": 4, "is_deleted": false}, "model": "party.party", "pk": 90}, {"fields": {"country": 3, "is_deleted": false}, "model": "party.party", "pk": 91}, {"fields": {"country": 3, "is_deleted": false}, "model": "party.party", "pk": 92}, {"fields": {"country": 4, "is_deleted": false}, "model": "party.party", "pk": 93}, {"fields": {"country": 4, "is_deleted": false}, "model": "party.party", "pk": 94}, {"fields": {"country": 6, "is_deleted": false}, "model": "party.party", "pk": 95}, {"fields": {"country": 1, "is_deleted": false}, "model": "party.party", "pk": 96}, {"fields": {"country": 1, "is_deleted": false}, "model": "party.party", "pk": 97}, {"fields": {"country": 3, "is_deleted": false}, "model": "party.party", "pk": 98}, {"fields": {"country": 2, "is_deleted": false}, "model": "party.party", "pk": 99}, {"fields": {"country": 1, "is_deleted": false}, "model": "party.party", "pk": 100}, {"fields": {"country": 2, "is_deleted": false}, "model": "party.party", "pk": 101}, {"fields": {"country": 6, "is_deleted": false}, "model": "party.party", "pk": 102}, {"fields": {"country": 3, "is_deleted": false}, "model": "party.party", "pk": 103}, {"fields": {"country": 6, "is_deleted": false}, "model": "party.party", "pk": 104}, {"fields": {"country": 1, "is_deleted": false}, "model": "party.party", "pk": 105}, {"fields": {"country": 2, "is_deleted": false}, "model": "party.party", "pk": 106}, {"fields": {"country": 4, "is_deleted": false}, "model": "party.party", "pk": 107}, {"fields": {"country": 4, "is_deleted": false}, "model": "party.party", "pk": 108}, {"fields": {"country": 5, "is_deleted": false}, "model": "party.party", "pk": 109}, {"fields": {"country": 3, "is_deleted": false}, "model": "party.party", "pk": 110}, {"fields": {"country": 6, "is_deleted": false}, "model": "party.party", "pk": 111}, {"fields": {"country": 5, "is_deleted": false}, "model": "party.party", "pk": 112}, {"fields": {"country": 2, "is_deleted": false}, "model": "party.party", "pk": 113}, {"fields": {"country": 6, "is_deleted": false}, "model": "party.party", "pk": 114}, {"fields": {"country": 5, "is_deleted": false}, "model": "party.party", "pk": 115}, {"fields": {"country": 6, "is_deleted": false}, "model": "party.party", "pk": 116}, {"fields": {"country": 7, "is_deleted": false}, "model": "party.party", "pk": 117}, {"fields": {"country": 2, "is_deleted": false}, "model": "party.party", "pk": 118}, {"fields": {"country": 4, "is_deleted": false}, "model": "party.party", "pk": 119}, {"fields": {"country": 7, "is_deleted": false}, "model": "party.party", "pk": 120}, {"fields": {"country": 2, "is_deleted": false}, "model": "party.party", "pk": 121}, {"fields": {"country": 2, "is_deleted": false}, "model": "party.party", "pk": 122}, {"fields": {"country": 3, "is_deleted": false}, "model": "party.party", "pk": 123}, {"fields": {"country": 1, "is_deleted": false}, "model": "party.party", "pk": 124}, {"fields": {"country": 2, "is_deleted": false}, "model": "party.party", "pk": 125}, {"fields": {"country": 1, "is_deleted": false}, "model": "party.party", "pk": 126}, {"fields": {"country": 6, "is_deleted": false}, "model": "party.party", "pk": 127}, {"fields": {"country": 1, "is_deleted": false}, "model": "party.party", "pk": 128}, {"fields": {"country": 2, "is_deleted": false}, "model": "party.party", "pk": 129}, {"fields": {"country": 6, "is_deleted": false}, "model": "party.party", "pk": 130}, {"fields": {"country": 1, "is_deleted": false}, "model": "party.party", "pk": 131}, {"fields": {"country": 7, "is_deleted": false}, "model": "party.party", "pk": 132}, {"fields": {"country": 6, "is_deleted": false}, "model": "party.party", "pk": 133}, {"fields": {"country": 6, "is_deleted": false}, "model": "party.party", "pk": 134}, {"fields": {"country": 5, "is_deleted": false}, "model": "party.party", "pk": 135}, {"fields": {"country": 5, "is_deleted": false}, "model": "party.party", "pk": 136}, {"fields": {"country": 1, "is_deleted": false}, "model": "party.party", "pk": 137}, {"fields": {"country": 1, "is_deleted": false}, "model": "party.party", "pk": 138}, {"fields": {"country": 1, "is_deleted": false}, "model": "party.party", "pk": 139}, {"fields": {"country": 7, "is_deleted": false}, "model": "party.party", "pk": 140}, {"fields": {"country": 5, "is_deleted": false}, "model": "party.party", "pk": 141}, {"fields": {"country": 1, "is_deleted": false}, "model": "party.party", "pk": 142}, {"fields": {"country": 6, "is_deleted": false}, "model": "party.party", "pk": 143}, {"fields": {"country": 7, "is_deleted": false}, "model": "party.party", "pk": 144}, {"fields": {"country": 4, "is_deleted": false}, "model": "party.party", "pk": 145}, {"fields": {"country": 5, "is_deleted": false}, "model": "party.party", "pk": 146}, {"fields": {"country": 1, "is_deleted": false}, "model": "party.party", "pk": 147}, {"fields": {"country": 6, "is_deleted": false}, "model": "party.party", "pk": 148}, {"fields": {"country": 2, "is_deleted": false}, "model": "party.party", "pk": 149}, {"fields": {"country": 4, "is_deleted": false}, "model": "party.party", "pk": 150}, {"fields": {"country": 7, "is_deleted": false}, "model": "party.party", "pk": 151}, {"fields": {"country": 6, "is_deleted": false}, "model": "party.party", "pk": 152}, {"fields": {"country": 4, "is_deleted": false}, "model": "party.party", "pk": 153}, {"fields": {"country": 1, "is_deleted": false}, "model": "party.party", "pk": 154}, {"fields": {"country": 4, "is_deleted": false}, "model": "party.party", "pk": 155}, {"fields": {"country": 7, "is_deleted": false}, "model": "party.party", "pk": 156}, {"fields": {"country": 2, "is_deleted": false}, "model": "party.party", "pk": 157}, {"fields": {"country": 5, "is_deleted": false}, "model": "party.party", "pk": 158}, {"fields": {"country": 5, "is_deleted": false}, "model": "party.party", "pk": 159}, {"fields": {"country": 3, "is_deleted": false}, "model": "party.party", "pk": 160}, {"fields": {"country": 7, "is_deleted": false}, "model": "party.party", "pk": 161}, {"fields": {"country": 7, "is_deleted": false}, "model": "party.party", "pk": 162}, {"fields": {"country": 6, "is_deleted": false}, "model": "party.party", "pk": 163}, {"fields": {"country": 2, "is_deleted": false}, "model": "party.party", "pk": 164}, {"fields": {"country": 5, "is_deleted": false}, "model": "party.party", "pk": 165}, {"fields": {"country": 3, "is_deleted": false}, "model": "party.party", "pk": 166}, {"fields": {"country": 6, "is_deleted": false}, "model": "party.party", "pk": 167}, {"fields": {"country": 4, "is_deleted": false}, "model": "party.party", "pk": 168}, {"fields": {"country": 1, "is_deleted": false}, "model": "party.party", "pk": 169}, {"fields": {"country": 7, "is_deleted": false}, "model": "party.party", "pk": 170}, {"fields": {"country": 3, "is_deleted": false}, "model": "party.party", "pk": 171}, {"fields": {"country": 4, "is_deleted": false}, "model": "party.party", "pk": 172}, {"fields": {"country": 1, "is_deleted": false}, "model": "party.party", "pk": 173}, {"fields": {"country": 3, "is_deleted": false}, "model": "party.party", "pk": 174}, {"fields": {"country": 1, "is_deleted": false}, "model": "party.party", "pk": 175}, {"fields": {"country": 1, "is_deleted": false}, "model": "party.party", "pk": 176}, {"fields": {"country": 5, "is_deleted": false}, "model": "party.party", "pk": 177}, {"fields": {"country": 3, "is_deleted": false}, "model": "party.party", "pk": 178}, {"fields": {"country": 4, "is_deleted": false}, "model": "party.party", "pk": 179}, {"fields": {"country": 2, "is_deleted": false}, "model": "party.party", "pk": 180}, {"fields": {"country": 7, "is_deleted": false}, "model": "party.party", "pk": 181}, {"fields": {"country": 6, "is_deleted": false}, "model": "party.party", "pk": 182}, {"fields": {"country": 6, "is_deleted": false}, "model": "party.party", "pk": 183}, {"fields": {"country": 5, "is_deleted": false}, "model": "party.party", "pk": 184}, {"fields": {"country": 6, "is_deleted": false}, "model": "party.party", "pk": 185}, {"fields": {"country": 3, "is_deleted": false}, "model": "party.party", "pk": 186}, {"fields": {"country": null, "is_deleted": false}, "model": "party.party", "pk": 187}, {"fields": {"country": 6, "is_deleted": false}, "model": "party.party", "pk": 188}, {"fields": {"country": 6, "is_deleted": false}, "model": "party.party", "pk": 189}, {"fields": {"country": null, "is_deleted": false}, "model": "party.party", "pk": 190}]